[
	{
		"name": "Mini HTMLs",
		"description": "Random assortment of small projects with HTML, CSS, and JS.",
		"link": "https://hans5958.github.io/mini-htmls/",
		"image": "/assets/img/highlights/mini-htmls.png"
	},
	{
		"name": "Hyper Flexible Timer",
		"description": "A timer/stopwatch hybrid that focuses on flexibility and simplicity. Built with Vue 3 and Astro.",
		"link": "https://hans5958.github.io/hyper-flexible-timer/",
		"image": "/assets/img/highlights/hyper-flexible-timer.png"
	},
	{
		"name": "Userscripts",
		"description": "A collection of userscripts and userstyles, free to use.",
		"link": "https://hans5958.github.io/userscripts/",
		"image": "/assets/img/highlights/userscripts.png"
	},
	{
		"name": "Domino English Translation",
		"description": "A project to translate Domino, a Japanese MIDI editor.",
		"link": "https://github.com/Hans5958/Domino-English-Translation",
		"image": "/assets/img/highlights/domino-english-translation.png"
	},
	{
		"name": "Scratch Addons",
		"description": "A browser extension for Scratch website. Mainly as a website maintainer.",
		"link": "https://scratchaddons.com",
		"image": "https://scratchaddons.com/assets/img/showcase/popup-light.png"
	},
	{
		"name": "The 2022 r/place Atlas",
		"description": "A project to catalog all the artworks of Reddit's 2022 r/place event. Worked with a team to remaster the website.",
		"link": "https://place-atlas.stefanocoding.me/",
		"image": "/assets/img/highlights/place-atlas.png"
	},
	{
		"name": "Black MIDI Meta",
		"description": "Repository of Black MIDI meta texts and stuff.",
		"link": "https://github.com/Hans5958/Black-MIDI-Meta"
	},
	{
		"name": "Pixel Adblock Filters",
		"description": "Personal ad block filters (it blocks more than ads). Mainly made for uBlock Origin",
		"link": "https://github.com/Hans5958/Pixel-Adblock-Filters"
	},
	{
		"name": "MediaWiki Scripts",
		"description": "Collection of scripts for editing in MediaWiki sites (also known as wikis), such as Wikipedia, Fandom, etc",
		"link": "https://gitlab.com/Hans5958-MWS"
	}
]